async_gelf_client-0.2.1.dist-info/licenses/LICENSE
asyncgelf/__init__.py
asyncgelf/client.py
asyncgelf/message.py
async_gelf_client-0.2.1.dist-info/METADATA
async_gelf_client-0.2.1.dist-info/WHEEL
async_gelf_client-0.2.1.dist-info/top_level.txt
async_gelf_client-0.2.1.dist-info/RECORD
