Metadata-Version: 2.4
Name: async-gelf-client
Version: 0.2.1
Summary: Async UDP client for sending GELF messages to Graylog
Author-email: Ivan Sheiko <gazziiii777@gmail.com>
License: MIT
Project-URL: Homepage, https://github.com/gazziiii777
Project-URL: Repository, https://github.com/gazziiii777/async-gelf-client
Keywords: gelf,graylog,logging,async,udp
Classifier: Development Status :: 4 - Beta
Classifier: Intended Audience :: Developers
Classifier: License :: OSI Approved :: MIT License
Classifier: Programming Language :: Python :: 3
Classifier: Programming Language :: Python :: 3.10
Classifier: Programming Language :: Python :: 3.11
Classifier: Programming Language :: Python :: 3.12
Classifier: Topic :: System :: Logging
Requires-Python: >=3.10
License-File: LICENSE
Dynamic: license-file
